DustyDisk/Constants.py
DustyDisk/Functions.py
DustyDisk/Plotting.py
DustyDisk/__init__.py
docs/conf.py
dustydisk-1.1.0.dist-info/licenses/LICENSE
tests/test_end_to_end.py
tests/test_unit.py
dustydisk-1.1.0.dist-info/METADATA
dustydisk-1.1.0.dist-info/WHEEL
dustydisk-1.1.0.dist-info/top_level.txt
dustydisk-1.1.0.dist-info/RECORD
