Metadata-Version: 2.4
Name: DustyDisk
Version: 1.1.0
License: MIT
License-File: LICENSE
Requires-Dist: numpy
Requires-Dist: matplotlib
Requires-Dist: sphinx
Requires-Dist: sphinx_rtd_theme
Dynamic: license-file
